goodboy_mongoengine/__init__.py
goodboy_mongoengine/document.py
goodboy_mongoengine/document_key.py
goodboy_mongoengine/field.py
goodboy_mongoengine/field_schemas.py
goodboy_mongoengine/messages.py
goodboy_mongoengine/py.typed
goodboy_mongoengine/schemas.py
goodboy_mongoengine-0.2.2.dist-info/LICENSE
goodboy_mongoengine-0.2.2.dist-info/METADATA
goodboy_mongoengine-0.2.2.dist-info/WHEEL
goodboy_mongoengine-0.2.2.dist-info/RECORD
