Metadata-Version: 2.1
Name: goodboy-mongoengine
Version: 0.2.2
Summary: Data validation tool for MongoEngine
License: MIT
Author: Maxim Andryunin
Author-email: maxim.andryunin@gmail.com
Requires-Python: >=3.7,<4.0
Classifier: License :: OSI Approved :: MIT License
Classifier: Programming Language :: Python :: 3
Classifier: Programming Language :: Python :: 3.7
Classifier: Programming Language :: Python :: 3.8
Classifier: Programming Language :: Python :: 3.9
Classifier: Programming Language :: Python :: 3.10
Classifier: Programming Language :: Python :: 3.11
Requires-Dist: goodboy (>=0.2,<0.3)
Requires-Dist: mongoengine
Requires-Dist: typing-extensions (>=4.0) ; python_version >= "3.6" and python_version < "3.8"
